LICENSE
MANIFEST.in
README.rst
setup.py
src/manage.py
src/minisentry/__init__.py
src/minisentry/__main__.py
src/minisentry/admin.py
src/minisentry/apps.py
src/minisentry/constants.py
src/minisentry/email.py
src/minisentry/helpers.py
src/minisentry/models.py
src/minisentry/mule.py
src/minisentry/settings.py
src/minisentry/tasks.py
src/minisentry/urls.py
src/minisentry/wsgi.py
src/minisentry.egg-info/PKG-INFO
src/minisentry.egg-info/SOURCES.txt
src/minisentry.egg-info/dependency_links.txt
src/minisentry.egg-info/entry_points.txt
src/minisentry.egg-info/not-zip-safe
src/minisentry.egg-info/requires.txt
src/minisentry.egg-info/top_level.txt
src/minisentry/migrations/0001_initial.py
src/minisentry/migrations/0002_auto_20180403_2025.py
src/minisentry/migrations/__init__.py
src/minisentry/static/.DS_Store
src/minisentry/static/minisentry/.DS_Store
src/minisentry/static/minisentry/css/bootstrap.min.css
src/minisentry/static/minisentry/css/bootstrap.min.css.map
src/minisentry/static/minisentry/js/bootstrap.min.js
src/minisentry/static/minisentry/js/bootstrap.min.js.map
src/minisentry/static/minisentry/js/jquery-3.2.1.slim.min.js
src/minisentry/static/minisentry/js/popper-1.12.9.min.js
src/minisentry/static/minisentry/js/popper.min.js.map
src/minisentry/templates/base.html
src/minisentry/templates/dashboard.html
src/minisentry/templates/group.html
src/minisentry/templates/groups_list.html
src/minisentry/templates/signin.html
src/minisentry/templates/signout.html
src/minisentry/templates/emails/group_created.html
src/minisentry/templates/include/projects_menu.html
src/minisentry/templates/include/table_from_dict.html
src/minisentry/views/__init__.py
src/minisentry/views/api.py
src/minisentry/views/auth.py
src/minisentry/views/events.py
src/minisentry/views/projects.py