Metadata-Version: 2.1
Name: minisentry
Version: 0.0.1
Summary: MiniSentry. Stripped Sentry replacement for development
Home-page: https://github.com/anti1869/minisentry/
Author: Dmitry Litvinenko
Author-email: anti1869@gmail.com
License: Proprietary
Platform: UNKNOWN
Classifier: License :: OSI Approved :: Apache Software License
Classifier: Intended Audience :: Developers
Classifier: Programming Language :: Python
Classifier: Programming Language :: Python :: 3
Classifier: Programming Language :: Python :: 3.6
Classifier: Topic :: Internet :: Log Analysis
Classifier: Topic :: Internet :: WWW/HTTP
Classifier: Topic :: Software Development :: Bug Tracking
Classifier: Framework :: Django :: 2.0
Provides-Extra: develop
